[
  {
    "name": "Mac mini ricondizionato, chip Apple M2 con CPU 8\u2010core e GPU 10\u2010core",
    "family": "mac",
    "store": "it",
    "url": "https://www.apple.com/it/shop/product/FMFJ3T/A/mac-mini-ricondizionato-chip-apple-m2-con-cpu-8%E2%80%91core-e-gpu-10%E2%80%91core",
    "price": 519.0,
    "previous_price": 609.0,
    "savings_price": 90.0,
    "saving_percentage": 0.1477832512315271,
    "model": "FMFJ3T"
  },
  {
    "name": "MacBook Air 13,3\" ricondizionato con chip Apple M1, CPU 8\u2010core e GPU 7\u2010core - Argento",
    "family": "mac",
    "store": "it",
    "url": "https://www.apple.com/it/shop/product/FGN93T/A/macbook-air-133-ricondizionato-con-chip-apple-m1-cpu-8%E2%80%91core-e-gpu-7%E2%80%91core-argento",
    "price": 869.0,
    "previous_price": 1229.0,
    "savings_price": 360.0,
    "saving_percentage": 0.29292107404393813,
    "model": "FGN93T"
  },
  {
    "name": "MacBook Air 13,3\" ricondizionato con chip Apple M1, CPU 8\u2010core e GPU 7\u2010core - Oro",
    "family": "mac",
    "store": "it",
    "url": "https://www.apple.com/it/shop/product/FGND3T/A/macbook-air-133-ricondizionato-con-chip-apple-m1-cpu-8%E2%80%91core-e-gpu-7%E2%80%91core-oro",
    "price": 869.0,
    "previous_price": 1229.0,
    "savings_price": 360.0,
    "saving_percentage": 0.29292107404393813,
    "model": "FGND3T"
  },
  {
    "name": "MacBook Air 13\" ricondizionato con chip Apple M2, CPU 8\u2010core e GPU 8\u2010core - Grigio siderale",
    "family": "mac",
    "store": "it",
    "url": "https://www.apple.com/it/shop/product/FLXW3T/A/MacBook-Air-13-ricondizionato-con-chip-Apple-M2-CPU-8%E2%80%91core-e-GPU-8%E2%80%91core-Grigio-siderale",
    "price": 959.0,
    "previous_price": 1129.0,
    "savings_price": 170.0,
    "saving_percentage": 0.15057573073516387,
    "model": "FLXW3T"
  },
  {
    "name": "MacBook Air 13\" ricondizionato con chip Apple M2, CPU 8\u2010core e GPU 8\u2010core - Galassia",
    "family": "mac",
    "store": "it",
    "url": "https://www.apple.com/it/shop/product/FLY13T/A/refurbished-13-inch-macbook-air-apple-m2-chip-with-8%E2%80%91core-cpu-and-8%E2%80%91core-gpu-starlight",
    "price": 959.0,
    "previous_price": 1129.0,
    "savings_price": 170.0,
    "saving_percentage": 0.15057573073516387,
    "model": "FLY13T"
  },
  {
    "name": "MacBook Air 13\" ricondizionato con chip Apple M2, CPU 8\u2010core e GPU 8\u2010core - Mezzanotte",
    "family": "mac",
    "store": "it",
    "url": "https://www.apple.com/it/shop/product/FLY33T/A/refurbished-13-inch-macbook-air-apple-m2-chip-with-8%E2%80%91core-cpu-and-8%E2%80%91core-gpu-midnight",
    "price": 959.0,
    "previous_price": 1129.0,
    "savings_price": 170.0,
    "saving_percentage": 0.15057573073516387,
    "model": "FLY33T"
  },
  {
    "name": "MacBook Air 13,3\" ricondizionato con chip Apple M1, CPU 8\u2010core e GPU 7\u2010core - Grigio siderale",
    "family": "mac",
    "store": "it",
    "url": "https://www.apple.com/it/shop/product/G1240T/A/macbook-air-133-ricondizionato-con-chip-apple-m1-cpu-8%E2%80%91core-e-gpu-7%E2%80%91core-grigio-siderale",
    "price": 1029.0,
    "previous_price": 1029.0,
    "savings_price": 0,
    "saving_percentage": 0.0,
    "model": "G1240T"
  },
  {
    "name": "MacBook Air 13\" ricondizionato con chip Apple M3, CPU 8\u2010core e GPU 8\u2010core - Grigio siderale",
    "family": "mac",
    "store": "it",
    "url": "https://www.apple.com/it/shop/product/FRXN3T/A/MacBook-Air-13-ricondizionato-con-chip-Apple-M3-CPU-8-core-e-GPU-8-core-Grigio-siderale",
    "price": 1039.0,
    "previous_price": 1229.0,
    "savings_price": 190.0,
    "saving_percentage": 0.15459723352318958,
    "model": "FRXN3T"
  },
  {
    "name": "MacBook Air 13\" ricondizionato con chip Apple M3, CPU 8\u2010core e GPU 8\u2010core - Argento",
    "family": "mac",
    "store": "it",
    "url": "https://www.apple.com/it/shop/product/FRXQ3T/A/MacBook-Air-13-pollici-ricondizionato-con-chip-Apple-M3-CPU-8-core-e-GPU-8-core-Argento",
    "price": 1039.0,
    "previous_price": 1229.0,
    "savings_price": 190.0,
    "saving_percentage": 0.15459723352318958,
    "model": "FRXQ3T"
  },
  {
    "name": "MacBook Air 13\" ricondizionato con chip Apple M3, CPU 8\u2010core e GPU 8\u2010core - Galassia",
    "family": "mac",
    "store": "it",
    "url": "https://www.apple.com/it/shop/product/FRXT3T/A/MacBook-Air-13-ricondizionato-con-chip-Apple-M3-CPU-8-core-e-GPU-8-core-Galassia",
    "price": 1039.0,
    "previous_price": 1229.0,
    "savings_price": 190.0,
    "saving_percentage": 0.15459723352318958,
    "model": "FRXT3T"
  },
  {
    "name": "MacBook Air 13\" ricondizionato con chip Apple M3, CPU 8\u2010core e GPU 8\u2010core - Mezzanotte",
    "family": "mac",
    "store": "it",
    "url": "https://www.apple.com/it/shop/product/FRXV3T/A/MacBook-Air-13-ricondizionato-con-chip-Apple-M3-CPU-8-core-e-GPU-8-core-Mezzanotte",
    "price": 1039.0,
    "previous_price": 1229.0,
    "savings_price": 190.0,
    "saving_percentage": 0.15459723352318958,
    "model": "FRXV3T"
  },
  {
    "name": "MacBook Air 13,3\" ricondizionato con chip Apple M1, CPU 8\u2010core e GPU 8\u2010core - Grigio siderale",
    "family": "mac",
    "store": "it",
    "url": "https://www.apple.com/it/shop/product/FGN73T/A/macbook-air-133-ricondizionato-con-chip-apple-m1-cpu-8%E2%80%91core-e-gpu-8%E2%80%91core-grigio-siderale",
    "price": 1049.0,
    "previous_price": 1429.0,
    "savings_price": 380.0,
    "saving_percentage": 0.26592022393282017,
    "model": "FGN73T"
  },
  {
    "name": "MacBook Air 13,3\" ricondizionato con chip Apple M1, CPU 8\u2010core e GPU 8\u2010core - Argento",
    "family": "mac",
    "store": "it",
    "url": "https://www.apple.com/it/shop/product/FGNA3T/A/macbook-air-133-ricondizionato-con-chip-apple-m1-cpu-8%E2%80%91core-e-gpu-8%E2%80%91core-argento",
    "price": 1049.0,
    "previous_price": 1429.0,
    "savings_price": 380.0,
    "saving_percentage": 0.26592022393282017,
    "model": "FGNA3T"
  },
  {
    "name": "iMac 24\" ricondizionato con chip Apple M1, CPU 8\u2010core e GPU 7\u2010core - Argento",
    "family": "mac",
    "store": "it",
    "url": "https://www.apple.com/it/shop/product/FGTF3T/A/iMac-24-ricondizionato-con-chip-Apple-M1-CPU-8%E2%80%91core-e-GPU-7%E2%80%91core-Argento",
    "price": 1139.0,
    "previous_price": 1569.0,
    "savings_price": 430.0,
    "saving_percentage": 0.27405991077119185,
    "model": "FGTF3T"
  },
  {
    "name": "iMac 24\" ricondizionato con chip Apple M1, CPU 8\u2010core e GPU 7\u2010core - Verde",
    "family": "mac",
    "store": "it",
    "url": "https://www.apple.com/it/shop/product/FJV83T/A/iMac-24-ricondizionato-con-chip-Apple-M1-CPU-8%E2%80%91core-e-GPU-7%E2%80%91core-Verde",
    "price": 1139.0,
    "previous_price": 1569.0,
    "savings_price": 430.0,
    "saving_percentage": 0.27405991077119185,
    "model": "FJV83T"
  },
  {
    "name": "iMac 24\" ricondizionato con chip Apple M1, CPU 8\u2010core e GPU 7\u2010core - Blu",
    "family": "mac",
    "store": "it",
    "url": "https://www.apple.com/it/shop/product/FJV93T/A/iMac-24-ricondizionato-con-chip-Apple-M1-CPU-8%E2%80%91core-e-GPU-7%E2%80%91core-Blu",
    "price": 1139.0,
    "previous_price": 1569.0,
    "savings_price": 430.0,
    "saving_percentage": 0.27405991077119185,
    "model": "FJV93T"
  },
  {
    "name": "MacBook Air 13\" ricondizionato con chip Apple M2, CPU 8\u2010core e GPU 10\u2010core - Grigio siderale",
    "family": "mac",
    "store": "it",
    "url": "https://www.apple.com/it/shop/product/FLXX3T/A/refurbished-13-inch-macbook-air-apple-m2-chip-with-8%E2%80%91core-cpu-and-10%E2%80%91core-gpu-space-gray",
    "price": 1159.0,
    "previous_price": 1369.0,
    "savings_price": 210.0,
    "saving_percentage": 0.15339663988312638,
    "model": "FLXX3T"
  },
  {
    "name": "MacBook Air 13\" ricondizionato con chip Apple M2, CPU 8\u2010core e GPU 10\u2010core - Galassia",
    "family": "mac",
    "store": "it",
    "url": "https://www.apple.com/it/shop/product/FLY23T/A/refurbished-13-inch-macbook-air-apple-m2-chip-with-8%E2%80%91core-cpu-and-10%E2%80%91core-gpu-starlight",
    "price": 1159.0,
    "previous_price": 1369.0,
    "savings_price": 210.0,
    "saving_percentage": 0.15339663988312638,
    "model": "FLY23T"
  },
  {
    "name": "MacBook Air 15\" ricondizionato con chip Apple M2, CPU 8\u2010core e GPU 10\u2010core - Argento",
    "family": "mac",
    "store": "it",
    "url": "https://www.apple.com/it/shop/product/FQKR3T/A/macbook-air-15-pollici-ricondizionato-con-chip-apple-m2-cpu-8%E2%80%91core-e-gpu-10%E2%80%91core-argento",
    "price": 1209.0,
    "previous_price": 1519.0,
    "savings_price": 310.0,
    "saving_percentage": 0.20408163265306123,
    "model": "FQKR3T"
  },
  {
    "name": "MacBook Air 15\" ricondizionato con chip Apple M2, CPU 8\u2010core e GPU 10\u2010core - Galassia",
    "family": "mac",
    "store": "it",
    "url": "https://www.apple.com/it/shop/product/FQKU3T/A/macbook%C2%A0air-15-pollici-ricondizionato-con-chip-apple-m2-cpu-8%E2%80%91core-e-gpu-10%E2%80%91core-galassia",
    "price": 1209.0,
    "previous_price": 1519.0,
    "savings_price": 310.0,
    "saving_percentage": 0.20408163265306123,
    "model": "FQKU3T"
  },
  {
    "name": "MacBook Air 15\" ricondizionato con chip Apple M2, CPU 8\u2010core e GPU 10\u2010core - Mezzanotte",
    "family": "mac",
    "store": "it",
    "url": "https://www.apple.com/it/shop/product/FQKW3T/A/macbook-air-15-ricondizionato-con-chip-apple-m2-cpu-8%E2%80%91core-e-gpu-10%E2%80%91core-mezzanotte",
    "price": 1209.0,
    "previous_price": 1519.0,
    "savings_price": 310.0,
    "saving_percentage": 0.20408163265306123,
    "model": "FQKW3T"
  },
  {
    "name": "MacBook Air 13\" ricondizionato con chip Apple M3, CPU 8\u2010core e GPU 10\u2010core - Galassia",
    "family": "mac",
    "store": "it",
    "url": "https://www.apple.com/it/shop/product/FRXU3T/A/MacBook-Air-13-ricondizionato-con-chip-Apple-M3-CPU-8-core-e-GPU-10-core-Galassia",
    "price": 1239.0,
    "previous_price": 1459.0,
    "savings_price": 220.0,
    "saving_percentage": 0.15078821110349555,
    "model": "FRXU3T"
  },
  {
    "name": "MacBook Air 13\" ricondizionato con chip Apple M3, CPU 8\u2010core e GPU 10\u2010core - Mezzanotte",
    "family": "mac",
    "store": "it",
    "url": "https://www.apple.com/it/shop/product/FRXW3T/A/MacBook-Air-13-ricondizionato-con-chip-Apple-M3-CPU-8-core-e-GPU-10-core-Mezzanotte",
    "price": 1239.0,
    "previous_price": 1459.0,
    "savings_price": 220.0,
    "saving_percentage": 0.15078821110349555,
    "model": "FRXW3T"
  },
  {
    "name": "MacBook Air 15\" ricondizionato con chip Apple M3, CPU 8\u2010core e GPU 10\u2010core - Grigio siderale",
    "family": "mac",
    "store": "it",
    "url": "https://www.apple.com/it/shop/product/FRYM3T/A/MacBook-Air-15-pollici-ricondizionato-con-chip-Apple-M3-CPU-8-core-e-GPU-10-core-Grigio-siderale",
    "price": 1299.0,
    "previous_price": 1529.0,
    "savings_price": 230.0,
    "saving_percentage": 0.15042511445389142,
    "model": "FRYM3T"
  },
  {
    "name": "MacBook Air 15\" ricondizionato con chip Apple M3, CPU 8\u2010core e GPU 10\u2010core - Galassia",
    "family": "mac",
    "store": "it",
    "url": "https://www.apple.com/it/shop/product/FRYR3T/A/MacBook-Air-15-pollici-ricondizionato-con-chip-Apple-M3-CPU-8-core-e-GPU-10%E2%80%91core-Galassia",
    "price": 1299.0,
    "previous_price": 1529.0,
    "savings_price": 230.0,
    "saving_percentage": 0.15042511445389142,
    "model": "FRYR3T"
  },
  {
    "name": "iMac 24\" ricondizionato con chip Apple M1, CPU 8\u2010core e GPU 7\u2010core - Blu",
    "family": "mac",
    "store": "it",
    "url": "https://www.apple.com/it/shop/product/G14M2T/A/iMac-24-ricondizionato-con-chip-Apple-M1-CPU-8%E2%80%91core-e-GPU-7%E2%80%91core-Blu",
    "price": 1319.0,
    "previous_price": 1319.0,
    "savings_price": 0,
    "saving_percentage": 0.0,
    "model": "G14M2T"
  },
  {
    "name": "iMac 24\" ricondizionato con chip Apple M1, CPU 8\u2010core e GPU 8\u2010core, Gigabit Ethernet - Argento",
    "family": "mac",
    "store": "it",
    "url": "https://www.apple.com/it/shop/product/FGPC3T/A/iMac-24-ricondizionato-con-chip-Apple-M1-CPU-8%E2%80%91core-e-GPU-8%E2%80%91core-Gigabit-Ethernet-Argento",
    "price": 1329.0,
    "previous_price": 1799.0,
    "savings_price": 470.0,
    "saving_percentage": 0.2612562534741523,
    "model": "FGPC3T"
  },
  {
    "name": "iMac 24\" ricondizionato con chip Apple M1, CPU 8\u2010core e GPU 8\u2010core, Gigabit Ethernet - Giallo",
    "family": "mac",
    "store": "it",
    "url": "https://www.apple.com/it/shop/product/FGPF3T/A/iMac-24-ricondizionato-con-chip-Apple-M1-CPU-8%E2%80%91core-e-GPU-8%E2%80%91core-Gigabit-Ethernet-Argento",
    "price": 1329.0,
    "previous_price": 1799.0,
    "savings_price": 470.0,
    "saving_percentage": 0.2612562534741523,
    "model": "FGPF3T"
  },
  {
    "name": "iMac 24\" ricondizionato con chip Apple M1, CPU 8\u2010core e GPU 8\u2010core, Gigabit Ethernet - Verde",
    "family": "mac",
    "store": "it",
    "url": "https://www.apple.com/it/shop/product/FGPH3T/A/iMac-24-ricondizionato-con-chip-Apple-M1-CPU-8%E2%80%91core-e-GPU-8%E2%80%91core-Gigabit-Ethernet-Argento",
    "price": 1329.0,
    "previous_price": 1799.0,
    "savings_price": 470.0,
    "saving_percentage": 0.2612562534741523,
    "model": "FGPH3T"
  },
  {
    "name": "iMac 24\" ricondizionato con chip Apple M1, CPU 8\u2010core e GPU 8\u2010core, Gigabit Ethernet - Blu",
    "family": "mac",
    "store": "it",
    "url": "https://www.apple.com/it/shop/product/FGPK3T/A/iMac-24-ricondizionato-con-chip-Apple-M1-CPU-8%E2%80%91core-e-GPU-8%E2%80%91core-Gigabit-Ethernet-Argento",
    "price": 1329.0,
    "previous_price": 1799.0,
    "savings_price": 470.0,
    "saving_percentage": 0.2612562534741523,
    "model": "FGPK3T"
  },
  {
    "name": "iMac 24\" ricondizionato con chip Apple M1, CPU 8\u2010core e GPU 8\u2010core, Gigabit Ethernet - Rosa",
    "family": "mac",
    "store": "it",
    "url": "https://www.apple.com/it/shop/product/FGPM3T/A/Refurbished-24-inch-iMac-Apple-M1-Chip-with-8%E2%80%91Core-CPU-and-8%E2%80%91Core-GPU-Gigabit-Ethernet-Silver",
    "price": 1329.0,
    "previous_price": 1799.0,
    "savings_price": 470.0,
    "saving_percentage": 0.2612562534741523,
    "model": "FGPM3T"
  },
  {
    "name": "iMac 24\" ricondizionato con chip Apple M1, CPU 8\u2010core e GPU 8\u2010core, Gigabit Ethernet - Viola",
    "family": "mac",
    "store": "it",
    "url": "https://www.apple.com/it/shop/product/FGPP3T/A/Refurbished-24-inch-iMac-Apple-M1-Chip-with-8%E2%80%91Core-CPU-and-8%E2%80%91Core-GPU-Gigabit-Ethernet-Silver",
    "price": 1329.0,
    "previous_price": 1799.0,
    "savings_price": 470.0,
    "saving_percentage": 0.2612562534741523,
    "model": "FGPP3T"
  },
  {
    "name": "iMac 24\" ricondizionato con chip Apple M3, CPU 8\u2010core e GPU 10\u2010core - Argento",
    "family": "mac",
    "store": "it",
    "url": "https://www.apple.com/it/shop/product/FQRJ3T/A/iMac-24-pollici-ricondizionato-con-chip-Apple-M3-CPU-8%E2%80%91core-e-GPU-10%E2%80%91core-Argento",
    "price": 1389.0,
    "previous_price": 1639.0,
    "savings_price": 250.0,
    "saving_percentage": 0.1525320317266626,
    "model": "FQRJ3T"
  },
  {
    "name": "iMac 24\" ricondizionato con chip Apple M3, CPU 8\u2010core e GPU 10\u2010core - Verde",
    "family": "mac",
    "store": "it",
    "url": "https://www.apple.com/it/shop/product/FQRN3T/A/iMac-24-pollici-ricondizionato-con-chip-Apple-M3-CPU-8%E2%80%91core-e-GPU-10%E2%80%91core-Verde",
    "price": 1389.0,
    "previous_price": 1639.0,
    "savings_price": 250.0,
    "saving_percentage": 0.1525320317266626,
    "model": "FQRN3T"
  },
  {
    "name": "iMac 24\" ricondizionato con chip Apple M3, CPU 8\u2010core e GPU 10\u2010core - Blu",
    "family": "mac",
    "store": "it",
    "url": "https://www.apple.com/it/shop/product/FQRQ3T/A/iMac-24-pollici-ricondizionato-con-chip-Apple-M3-CPU-8%E2%80%91core-e-GPU-10%E2%80%91core-Blu",
    "price": 1389.0,
    "previous_price": 1639.0,
    "savings_price": 250.0,
    "saving_percentage": 0.1525320317266626,
    "model": "FQRQ3T"
  },
  {
    "name": "MacBook Air 15\" ricondizionato con chip Apple M2, CPU 8\u2010core e GPU 10\u2010core - Mezzanotte",
    "family": "mac",
    "store": "it",
    "url": "https://www.apple.com/it/shop/product/FQKX3T/A/macbook-air-15-ricondizionato-con-chip-apple-m2-cpu-8%E2%80%91core-e-gpu-10%E2%80%91core-mezzanotte",
    "price": 1399.0,
    "previous_price": 1749.0,
    "savings_price": 350.0,
    "saving_percentage": 0.20011435105774728,
    "model": "FQKX3T"
  },
  {
    "name": "MacBook Air 13\" ricondizionato con chip Apple M2, CPU 8\u2010core e GPU 10\u2010core - Galassia",
    "family": "mac",
    "store": "it",
    "url": "https://www.apple.com/it/shop/product/G15Z3T/A/refurbished-13-inch-macbook-air-apple-m2-chip-with-8%E2%80%91core-cpu-and-10%E2%80%91core-gpu-starlight",
    "price": 1489.0,
    "previous_price": 1489.0,
    "savings_price": 0,
    "saving_percentage": 0.0,
    "model": "G15Z3T"
  },
  {
    "name": "MacBook Air 15\" ricondizionato con chip Apple M3, CPU 8\u2010core e GPU 10\u2010core - Argento",
    "family": "mac",
    "store": "it",
    "url": "https://www.apple.com/it/shop/product/FRYQ3T/A/MacBook-Air-15-pollici-ricondizionato-con-chip-Apple-M3-CPU-8-core-e-GPU-10-core-Argento",
    "price": 1499.0,
    "previous_price": 1759.0,
    "savings_price": 260.0,
    "saving_percentage": 0.14781125639567935,
    "model": "FRYQ3T"
  },
  {
    "name": "MacBook Air 15\" ricondizionato con chip Apple M3, CPU 8\u2010core e GPU 10\u2010core - Grigio siderale",
    "family": "mac",
    "store": "it",
    "url": "https://www.apple.com/it/shop/product/FRYN3T/A/MacBook-Air-15-pollici-ricondizionato-con-chip-Apple-M3-CPU-8-core-e-GPU-10-core-Grigio-siderale",
    "price": 1499.0,
    "previous_price": 1759.0,
    "savings_price": 260.0,
    "saving_percentage": 0.14781125639567935,
    "model": "FRYN3T"
  },
  {
    "name": "MacBook Air 15\" ricondizionato con chip Apple M3, CPU 8\u2010core e GPU 10\u2010core - Galassia",
    "family": "mac",
    "store": "it",
    "url": "https://www.apple.com/it/shop/product/FRYT3T/A/MacBook-Air-15-pollici-ricondizionato-con-chip-Apple-M3-CPU-8-core-e-GPU-10%E2%80%91core-Galassia",
    "price": 1499.0,
    "previous_price": 1759.0,
    "savings_price": 260.0,
    "saving_percentage": 0.14781125639567935,
    "model": "FRYT3T"
  },
  {
    "name": "MacBook Air 15\" ricondizionato con chip Apple M3, CPU 8\u2010core e GPU 10\u2010core - Mezzanotte",
    "family": "mac",
    "store": "it",
    "url": "https://www.apple.com/it/shop/product/FRYV3T/A/MacBook-Air-15-pollici-ricondizionato-con-chip-Apple-M3-CPU-8-core-e-GPU-10-core-Mezzanotte",
    "price": 1499.0,
    "previous_price": 1759.0,
    "savings_price": 260.0,
    "saving_percentage": 0.14781125639567935,
    "model": "FRYV3T"
  },
  {
    "name": "iMac 24\" ricondizionato con chip Apple M1, CPU 8\u2010core e GPU 8\u2010core, Gigabit Ethernet - Giallo",
    "family": "mac",
    "store": "it",
    "url": "https://www.apple.com/it/shop/product/FGPG3T/A/iMac-24-ricondizionato-con-chip-Apple-M1-CPU-8%E2%80%91core-e-GPU-8%E2%80%91core-Gigabit-Ethernet-Argento",
    "price": 1519.0,
    "previous_price": 2029.0,
    "savings_price": 510.0,
    "saving_percentage": 0.2513553474618038,
    "model": "FGPG3T"
  },
  {
    "name": "iMac 24\" ricondizionato con chip Apple M1, CPU 8\u2010core e GPU 8\u2010core, Gigabit Ethernet - Verde",
    "family": "mac",
    "store": "it",
    "url": "https://www.apple.com/it/shop/product/FGPJ3T/A/iMac-24-ricondizionato-con-chip-Apple-M1-CPU-8%E2%80%91core-e-GPU-8%E2%80%91core-Gigabit-Ethernet-Argento",
    "price": 1519.0,
    "previous_price": 2029.0,
    "savings_price": 510.0,
    "saving_percentage": 0.2513553474618038,
    "model": "FGPJ3T"
  },
  {
    "name": "iMac 24\" ricondizionato con chip Apple M1, CPU 8\u2010core e GPU 8\u2010core, Gigabit Ethernet - Blu",
    "family": "mac",
    "store": "it",
    "url": "https://www.apple.com/it/shop/product/FGPL3T/A/iMac-24-ricondizionato-con-chip-Apple-M1-CPU-8%E2%80%91core-e-GPU-8%E2%80%91core-Gigabit-Ethernet-Argento",
    "price": 1519.0,
    "previous_price": 2029.0,
    "savings_price": 510.0,
    "saving_percentage": 0.2513553474618038,
    "model": "FGPL3T"
  },
  {
    "name": "iMac 24\" ricondizionato con chip Apple M1, CPU 8\u2010core e GPU 8\u2010core, Gigabit Ethernet - Rosa",
    "family": "mac",
    "store": "it",
    "url": "https://www.apple.com/it/shop/product/FGPN3T/A/iMac-24-ricondizionato-con-chip-Apple-M1-CPU-8%E2%80%91core-e-GPU-8%E2%80%91core-Gigabit-Ethernet-Argento",
    "price": 1519.0,
    "previous_price": 2029.0,
    "savings_price": 510.0,
    "saving_percentage": 0.2513553474618038,
    "model": "FGPN3T"
  },
  {
    "name": "iMac 24\" ricondizionato con chip Apple M1, CPU 8\u2010core e GPU 8\u2010core, Gigabit Ethernet - Viola",
    "family": "mac",
    "store": "it",
    "url": "https://www.apple.com/it/shop/product/FGPQ3T/A/iMac-24-ricondizionato-con-chip-Apple-M1-CPU-8%E2%80%91core-e-GPU-8%E2%80%91core-Gigabit-Ethernet-Argento",
    "price": 1519.0,
    "previous_price": 2029.0,
    "savings_price": 510.0,
    "saving_percentage": 0.2513553474618038,
    "model": "FGPQ3T"
  },
  {
    "name": "iMac 24\" ricondizionato con chip Apple M1, CPU 8\u2010core e GPU 8\u2010core, Gigabit Ethernet - Arancione",
    "family": "mac",
    "store": "it",
    "url": "https://www.apple.com/it/shop/product/FGPT3T/A/iMac-24-ricondizionato-con-chip-Apple-M1-CPU-8%E2%80%91core-e-GPU-8%E2%80%91core-Gigabit-Ethernet-Argento",
    "price": 1519.0,
    "previous_price": 2029.0,
    "savings_price": 510.0,
    "saving_percentage": 0.2513553474618038,
    "model": "FGPT3T"
  },
  {
    "name": "Mac mini ricondizionato, chip Apple M2 Pro con CPU 10\u2010core e GPU 16\u2010core",
    "family": "mac",
    "store": "it",
    "url": "https://www.apple.com/it/shop/product/G1701T/A/mac-mini-ricondizionato-chip-apple-m2-pro-con-cpu-10%E2%80%91core-e-gpu-16%E2%80%91core",
    "price": 1519.0,
    "previous_price": 1519.0,
    "savings_price": 0,
    "saving_percentage": 0.0,
    "model": "G1701T"
  },
  {
    "name": "Apple Studio Display ricondizionato, vetro standard, sostegno a inclinazione regolabile",
    "family": "mac",
    "store": "it",
    "url": "https://www.apple.com/it/shop/product/FK0U3T/A/Apple-Studio-Display-ricondizionato-vetro-standard-sostegno-a-inclinazione-regolabile",
    "price": 1529.0,
    "previous_price": 1799.0,
    "savings_price": 270.0,
    "saving_percentage": 0.15008337965536409,
    "model": "FK0U3T"
  },
  {
    "name": "iMac 24\" ricondizionato con chip Apple M3, CPU 8\u2010core e GPU 10\u2010core - Blu",
    "family": "mac",
    "store": "it",
    "url": "https://www.apple.com/it/shop/product/G19K0T/A/iMac-24-pollici-ricondizionato-con-chip-Apple-M3-CPU-8%E2%80%91core-e-GPU-10%E2%80%91core-Blu",
    "price": 1559.0,
    "previous_price": 1559.0,
    "savings_price": 0,
    "saving_percentage": 0.0,
    "model": "G19K0T"
  },
  {
    "name": "iMac 24\" ricondizionato con chip Apple M3, CPU 8\u2010core e GPU 10\u2010core - Verde",
    "family": "mac",
    "store": "it",
    "url": "https://www.apple.com/it/shop/product/FQRP3T/A/iMac-24-pollici-ricondizionato-con-chip-Apple-M3-CPU-8%E2%80%91core-e-GPU-10%E2%80%91core-Verde",
    "price": 1589.0,
    "previous_price": 1869.0,
    "savings_price": 280.0,
    "saving_percentage": 0.149812734082397,
    "model": "FQRP3T"
  },
  {
    "name": "iMac 24\" ricondizionato con chip Apple M3, CPU 8\u2010core e GPU 10\u2010core - Blu",
    "family": "mac",
    "store": "it",
    "url": "https://www.apple.com/it/shop/product/FQRR3T/A/iMac-24-pollici-ricondizionato-con-chip-Apple-M3-CPU-8%E2%80%91core-e-GPU-10%E2%80%91core-Blu",
    "price": 1589.0,
    "previous_price": 1869.0,
    "savings_price": 280.0,
    "saving_percentage": 0.149812734082397,
    "model": "FQRR3T"
  },
  {
    "name": "Mac mini ricondizionato, chip Apple M2 Pro con CPU 10\u2010core e GPU 16\u2010core",
    "family": "mac",
    "store": "it",
    "url": "https://www.apple.com/it/shop/product/G1709T/A/mac-mini-ricondizionato-chip-apple-m2-pro-con-cpu-10%E2%80%91core-e-gpu-16%E2%80%91core",
    "price": 1719.0,
    "previous_price": 1719.0,
    "savings_price": 0,
    "saving_percentage": 0.0,
    "model": "G1709T"
  },
  {
    "name": "MacBook Air 15\" ricondizionato con chip Apple M2, CPU 8\u2010core e GPU 10\u2010core - Mezzanotte",
    "family": "mac",
    "store": "it",
    "url": "https://www.apple.com/it/shop/product/G18U5T/A/macbook-air-15-ricondizionato-con-chip-apple-m2-cpu-8%E2%80%91core-e-gpu-10%E2%80%91core-mezzanotte",
    "price": 1719.0,
    "previous_price": 1719.0,
    "savings_price": 0,
    "saving_percentage": 0.0,
    "model": "G18U5T"
  },
  {
    "name": "iMac 24\" ricondizionato con chip Apple M3, CPU 8\u2010core e GPU 10\u2010core - Blu",
    "family": "mac",
    "store": "it",
    "url": "https://www.apple.com/it/shop/product/G19L2T/A/iMac-24-pollici-ricondizionato-con-chip-Apple-M3-CPU-8%E2%80%91core-e-GPU-10%E2%80%91core-Blu",
    "price": 1729.0,
    "previous_price": 1729.0,
    "savings_price": 0,
    "saving_percentage": 0.0,
    "model": "G19L2T"
  },
  {
    "name": "Apple Studio Display ricondizionato, vetro nanotexture, sostegno a inclinazione regolabile",
    "family": "mac",
    "store": "it",
    "url": "https://www.apple.com/it/shop/product/FMYW3T/A/Apple-Studio-Display-ricondizionato-vetro-nanotexture-sostegno-a-inclinazione-regolabile",
    "price": 1739.0,
    "previous_price": 2049.0,
    "savings_price": 310.0,
    "saving_percentage": 0.15129331381161543,
    "model": "FMYW3T"
  },
  {
    "name": "MacBook Air 15\" ricondizionato con chip Apple M3, CPU 8\u2010core e GPU 10\u2010core - Grigio siderale",
    "family": "mac",
    "store": "it",
    "url": "https://www.apple.com/it/shop/product/G1BQ5T/A/MacBook-Air-15-pollici-ricondizionato-con-chip-Apple-M3-CPU-8-core-e-GPU-10-core-Grigio-siderale",
    "price": 1799.0,
    "previous_price": 1799.0,
    "savings_price": 0,
    "saving_percentage": 0.0,
    "model": "G1BQ5T"
  },
  {
    "name": "Mac mini ricondizionato, chip Apple M2 Pro con CPU 10\u2010core e GPU 16\u2010core",
    "family": "mac",
    "store": "it",
    "url": "https://www.apple.com/it/shop/product/G170BT/A/mac-mini-ricondizionato-chip-apple-m2-pro-con-cpu-10%E2%80%91core-e-gpu-16%E2%80%91core",
    "price": 1909.0,
    "previous_price": 1909.0,
    "savings_price": 0,
    "saving_percentage": 0.0,
    "model": "G170BT"
  },
  {
    "name": "MacBook Air 13\" ricondizionato con chip Apple M3, CPU 8\u2010core e GPU 10\u2010core - Mezzanotte",
    "family": "mac",
    "store": "it",
    "url": "https://www.apple.com/it/shop/product/G1BD4T/A/MacBook-Air-13-ricondizionato-con-chip-Apple-M3-CPU-8-core-e-GPU-10-core-Mezzanotte",
    "price": 1919.0,
    "previous_price": 1919.0,
    "savings_price": 0,
    "saving_percentage": 0.0,
    "model": "G1BD4T"
  },
  {
    "name": "MacBook Air 13\" ricondizionato con chip Apple M2, CPU 8\u2010core e GPU 10\u2010core - Grigio siderale",
    "family": "mac",
    "store": "it",
    "url": "https://www.apple.com/it/shop/product/G15T7T/A/refurbished-13-inch-macbook-air-apple-m2-chip-with-8%E2%80%91core-cpu-and-10%E2%80%91core-gpu-space-gray",
    "price": 2019.0,
    "previous_price": 2019.0,
    "savings_price": 0,
    "saving_percentage": 0.0,
    "model": "G15T7T"
  },
  {
    "name": "MacBook Air 13\" ricondizionato con chip Apple M2, CPU 8\u2010core e GPU 10\u2010core - Mezzanotte",
    "family": "mac",
    "store": "it",
    "url": "https://www.apple.com/it/shop/product/G1617T/A/refurbished-13-inch-macbook-air-apple-m2-chip-with-8%E2%80%91core-cpu-and-10%E2%80%91core-gpu-midnight",
    "price": 2019.0,
    "previous_price": 2019.0,
    "savings_price": 0,
    "saving_percentage": 0.0,
    "model": "G1617T"
  },
  {
    "name": "Apple Studio Display ricondizionato, vetro nanotexture, sostegno a inclinazione e altezza regolabili",
    "family": "mac",
    "store": "it",
    "url": "https://www.apple.com/it/shop/product/FMYV3T/A/Apple-Studio-Display-ricondizionato-vetro-nanotexture-sostegno-a-inclinazione-e-altezza-regolabili",
    "price": 2129.0,
    "previous_price": 2509.0,
    "savings_price": 380.0,
    "saving_percentage": 0.15145476285372658,
    "model": "FMYV3T"
  },
  {
    "name": "iMac 24\" ricondizionato con chip Apple M1, CPU 8\u2010core e GPU 8\u2010core, Gigabit Ethernet - Rosa",
    "family": "mac",
    "store": "it",
    "url": "https://www.apple.com/it/shop/product/G12Z4T/A/iMac-24-ricondizionato-con-chip-Apple-M1-CPU-8%E2%80%91core-e-GPU-8%E2%80%91core-Gigabit-Ethernet-Argento",
    "price": 2229.0,
    "previous_price": 2229.0,
    "savings_price": 0,
    "saving_percentage": 0.0,
    "model": "G12Z4T"
  },
  {
    "name": "iMac 24\" ricondizionato con chip Apple M3, CPU 8\u2010core e GPU 10\u2010core - Blu",
    "family": "mac",
    "store": "it",
    "url": "https://www.apple.com/it/shop/product/G19L7T/A/iMac-24-pollici-ricondizionato-con-chip-Apple-M3-CPU-8%E2%80%91core-e-GPU-10%E2%80%91core-Blu",
    "price": 2429.0,
    "previous_price": 2429.0,
    "savings_price": 0,
    "saving_percentage": 0.0,
    "model": "G19L7T"
  },
  {
    "name": "MacBook Pro 16\" ricondizionato con chip Apple M2 Pro, CPU 12\u2010core e GPU 19\u2010core - Grigio siderale",
    "family": "mac",
    "store": "it",
    "url": "https://www.apple.com/it/shop/product/G1753T/A/macbook-pro-16-ricondizionato-con-chip-apple-m2-pro-cpu-12%E2%80%91core-e-gpu-19%E2%80%91core-grigio-siderale",
    "price": 2909.0,
    "previous_price": 2909.0,
    "savings_price": 0,
    "saving_percentage": 0.0,
    "model": "G1753T"
  },
  {
    "name": "MacBook Pro 16\" ricondizionato con chip Apple M2 Pro, CPU 12\u2010core e GPU 19\u2010core - Argento",
    "family": "mac",
    "store": "it",
    "url": "https://www.apple.com/it/shop/product/G1783T/A/macbook-pro-16-ricondizionato-con-chip-apple-m2-pro-cpu-12%E2%80%91core-e-gpu-19%E2%80%91core-argento",
    "price": 2909.0,
    "previous_price": 2909.0,
    "savings_price": 0,
    "saving_percentage": 0.0,
    "model": "G1783T"
  },
  {
    "name": "MacBook Pro 14\" ricondizionato con chip Apple M3 Max con CPU 14\u2010core e GPU 30\u2010core - Nero siderale",
    "family": "mac",
    "store": "it",
    "url": "https://www.apple.com/it/shop/product/FRX53T/A/macbook-pro-14-pollici-ricondizionato-con-chip-apple-m3-max-con-cpu-14%E2%80%91core-e-gpu-30%E2%80%91core-nero-siderale",
    "price": 3209.0,
    "previous_price": 3779.0,
    "savings_price": 570.0,
    "saving_percentage": 0.15083355385022493,
    "model": "FRX53T"
  },
  {
    "name": "MacBook Pro 14\" ricondizionato con chip Apple M3 Max con CPU 14\u2010core e GPU 30\u2010core - Argento",
    "family": "mac",
    "store": "it",
    "url": "https://www.apple.com/it/shop/product/FRX83T/A/macbook-pro-14-pollici-ricondizionato-con-chip-apple-m3-max-con-cpu-14%E2%80%91core-e-gpu-30%E2%80%91core-argento",
    "price": 3209.0,
    "previous_price": 3779.0,
    "savings_price": 570.0,
    "saving_percentage": 0.15083355385022493,
    "model": "FRX83T"
  },
  {
    "name": "MacBook Pro 14\" ricondizionato con chip Apple M2 Max, CPU 12\u2010core e GPU 30\u2010core - Grigio siderale",
    "family": "mac",
    "store": "it",
    "url": "https://www.apple.com/it/shop/product/G17J0T/A/macbook-pro-14-ricondizionato-con-chip-apple-m2-max-cpu-12-core-e-gpu-30-core-grigio-siderale",
    "price": 3249.0,
    "previous_price": 3249.0,
    "savings_price": 0,
    "saving_percentage": 0.0,
    "model": "G17J0T"
  },
  {
    "name": "MacBook Pro 16\" ricondizionato con chip Apple M2 Pro, CPU 12\u2010core e GPU 19\u2010core - Grigio siderale",
    "family": "mac",
    "store": "it",
    "url": "https://www.apple.com/it/shop/product/G1754T/A/macbook-pro-16-ricondizionato-con-chip-apple-m2-pro-cpu-12%E2%80%91core-e-gpu-19%E2%80%91core-grigio-siderale",
    "price": 3259.0,
    "previous_price": 3259.0,
    "savings_price": 0,
    "saving_percentage": 0.0,
    "model": "G1754T"
  },
  {
    "name": "MacBook Pro 16\" ricondizionato con chip Apple M2 Max, CPU 12\u2010core e GPU 38\u2010core - Grigio siderale",
    "family": "mac",
    "store": "it",
    "url": "https://www.apple.com/it/shop/product/FNWA3T/A/macbook-pro-16-ricondizionato-con-chip-apple-m2-max-cpu-12%E2%80%91core-e-gpu-38%E2%80%91core-grigio-siderale",
    "price": 3349.0,
    "previous_price": 4219.0,
    "savings_price": 870.0,
    "saving_percentage": 0.2062100023702299,
    "model": "FNWA3T"
  },
  {
    "name": "MacBook Pro 16\" ricondizionato con chip Apple M2 Max, CPU 12\u2010core e GPU 38\u2010core - Argento",
    "family": "mac",
    "store": "it",
    "url": "https://www.apple.com/it/shop/product/FNWE3T/A/macbook-pro-16-ricondizionato-con-chip-apple-m2-max-cpu-12%E2%80%91core-e-gpu-38%E2%80%91core-argento",
    "price": 3349.0,
    "previous_price": 4219.0,
    "savings_price": 870.0,
    "saving_percentage": 0.2062100023702299,
    "model": "FNWE3T"
  },
  {
    "name": "MacBook Pro 16\" ricondizionato con chip Apple M2 Max, CPU 12\u2010core e GPU 30\u2010core - Grigio siderale",
    "family": "mac",
    "store": "it",
    "url": "https://www.apple.com/it/shop/product/G175BT/A/macbook-pro-16-ricondizionato-con-chip-apple-m2-max-cpu-12%E2%80%91core-e-gpu-30%E2%80%91core-grigio-siderale",
    "price": 3439.0,
    "previous_price": 3439.0,
    "savings_price": 0,
    "saving_percentage": 0.0,
    "model": "G175BT"
  },
  {
    "name": "MacBook Pro 16\" ricondizionato con chip Apple M2 Max, CPU 12\u2010core e GPU 38\u2010core - Grigio siderale",
    "family": "mac",
    "store": "it",
    "url": "https://www.apple.com/it/shop/product/G1760T/A/macbook-pro-16-ricondizionato-con-chip-apple-m2-max-cpu-12%E2%80%91core-e-gpu-38%E2%80%91core-grigio-siderale",
    "price": 3589.0,
    "previous_price": 3589.0,
    "savings_price": 0,
    "saving_percentage": 0.0,
    "model": "G1760T"
  },
  {
    "name": "MacBook Pro 14\" ricondizionato con chip Apple M2 Max, CPU 12\u2010core e GPU 30\u2010core - Grigio siderale",
    "family": "mac",
    "store": "it",
    "url": "https://www.apple.com/it/shop/product/G17J4T/A/macbook-pro-14-ricondizionato-con-chip-apple-m2-max-cpu-12-core-e-gpu-30-core-grigio-siderale",
    "price": 3599.0,
    "previous_price": 3599.0,
    "savings_price": 0,
    "saving_percentage": 0.0,
    "model": "G17J4T"
  },
  {
    "name": "MacBook Pro 14\" ricondizionato con chip Apple M2 Max, CPU 12\u2010core e GPU 30\u2010core - Argento",
    "family": "mac",
    "store": "it",
    "url": "https://www.apple.com/it/shop/product/G17M4T/A/macbook-pro-14-ricondizionato-con-chip-apple-m2-max-cpu-12-core-e-gpu-30-core-argento",
    "price": 3599.0,
    "previous_price": 3599.0,
    "savings_price": 0,
    "saving_percentage": 0.0,
    "model": "G17M4T"
  },
  {
    "name": "MacBook Pro 14\" ricondizionato con chip Apple M2 Max, CPU 12\u2010core e GPU 30\u2010core - Grigio siderale",
    "family": "mac",
    "store": "it",
    "url": "https://www.apple.com/it/shop/product/G17J1T/A/macbook-pro-14-ricondizionato-con-chip-apple-m2-max-cpu-12-core-e-gpu-30-core-grigio-siderale",
    "price": 3769.0,
    "previous_price": 3769.0,
    "savings_price": 0,
    "saving_percentage": 0.0,
    "model": "G17J1T"
  },
  {
    "name": "MacBook Pro 14\" ricondizionato con chip Apple M2 Max, CPU 12\u2010core e GPU 38\u2010core - Grigio siderale",
    "family": "mac",
    "store": "it",
    "url": "https://www.apple.com/it/shop/product/G17JCT/A/macbook-pro-14-ricondizionato-con-chip-apple-m2-max-cpu-12-core-e-gpu-38-core-grigio-siderale",
    "price": 3769.0,
    "previous_price": 3769.0,
    "savings_price": 0,
    "saving_percentage": 0.0,
    "model": "G17JCT"
  },
  {
    "name": "MacBook Pro 16\" ricondizionato con chip Apple M2 Max, CPU 12\u2010core e GPU 38\u2010core - Grigio siderale",
    "family": "mac",
    "store": "it",
    "url": "https://www.apple.com/it/shop/product/G1764T/A/macbook-pro-16-ricondizionato-con-chip-apple-m2-max-cpu-12%E2%80%91core-e-gpu-38%E2%80%91core-grigio-siderale",
    "price": 3939.0,
    "previous_price": 3939.0,
    "savings_price": 0,
    "saving_percentage": 0.0,
    "model": "G1764T"
  },
  {
    "name": "MacBook Pro 16\" ricondizionato con chip Apple M2 Max, CPU 12\u2010core e GPU 38\u2010core - Grigio siderale",
    "family": "mac",
    "store": "it",
    "url": "https://www.apple.com/it/shop/product/G1767T/A/macbook-pro-16-ricondizionato-con-chip-apple-m2-max-cpu-12%E2%80%91core-e-gpu-38%E2%80%91core-grigio-siderale",
    "price": 3939.0,
    "previous_price": 3939.0,
    "savings_price": 0,
    "saving_percentage": 0.0,
    "model": "G1767T"
  },
  {
    "name": "MacBook Pro 16\" ricondizionato con chip Apple M2 Max, CPU 12\u2010core e GPU 38\u2010core - Argento",
    "family": "mac",
    "store": "it",
    "url": "https://www.apple.com/it/shop/product/G1794T/A/macbook-pro-16-ricondizionato-con-chip-apple-m2-max-cpu-12%E2%80%91core-e-gpu-38%E2%80%91core-argento",
    "price": 3939.0,
    "previous_price": 3939.0,
    "savings_price": 0,
    "saving_percentage": 0.0,
    "model": "G1794T"
  },
  {
    "name": "MacBook Pro 16\" ricondizionato con chip Apple M3 Max, CPU 16\u2010core e GPU 40\u2010core - Nero siderale",
    "family": "mac",
    "store": "it",
    "url": "https://www.apple.com/it/shop/product/FUW63T/A/macbook-pro-16-ricondizionato-con-chip-apple-m3-max-cpu-16%E2%80%91core-e-gpu-40%E2%80%91core-nero-siderale",
    "price": 3979.0,
    "previous_price": 4679.0,
    "savings_price": 700.0,
    "saving_percentage": 0.14960461637101946,
    "model": "FUW63T"
  },
  {
    "name": "MacBook Pro 14\" ricondizionato con chip Apple M2 Max, CPU 12\u2010core e GPU 30\u2010core - Grigio siderale",
    "family": "mac",
    "store": "it",
    "url": "https://www.apple.com/it/shop/product/G17J5T/A/macbook-pro-14-ricondizionato-con-chip-apple-m2-max-cpu-12-core-e-gpu-30-core-grigio-siderale",
    "price": 4119.0,
    "previous_price": 4119.0,
    "savings_price": 0,
    "saving_percentage": 0.0,
    "model": "G17J5T"
  },
  {
    "name": "MacBook Pro 14\" ricondizionato con chip Apple M2 Max, CPU 12\u2010core e GPU 38\u2010core - Grigio siderale",
    "family": "mac",
    "store": "it",
    "url": "https://www.apple.com/it/shop/product/G17JGT/A/macbook-pro-14-ricondizionato-con-chip-apple-m2-max-cpu-12-core-e-gpu-38-core-grigio-siderale",
    "price": 4119.0,
    "previous_price": 4119.0,
    "savings_price": 0,
    "saving_percentage": 0.0,
    "model": "G17JGT"
  },
  {
    "name": "MacBook Pro 16\" ricondizionato con chip Apple M2 Max, CPU 12\u2010core e GPU 38\u2010core - Grigio siderale",
    "family": "mac",
    "store": "it",
    "url": "https://www.apple.com/it/shop/product/G1768T/A/macbook-pro-16-ricondizionato-con-chip-apple-m2-max-cpu-12%E2%80%91core-e-gpu-38%E2%80%91core-grigio-siderale",
    "price": 4289.0,
    "previous_price": 4289.0,
    "savings_price": 0,
    "saving_percentage": 0.0,
    "model": "G1768T"
  },
  {
    "name": "MacBook Pro 16\" ricondizionato con chip Apple M2 Max, CPU 12\u2010core e GPU 38\u2010core - Argento",
    "family": "mac",
    "store": "it",
    "url": "https://www.apple.com/it/shop/product/G1798T/A/macbook-pro-16-ricondizionato-con-chip-apple-m2-max-cpu-12%E2%80%91core-e-gpu-38%E2%80%91core-argento",
    "price": 4289.0,
    "previous_price": 4289.0,
    "savings_price": 0,
    "saving_percentage": 0.0,
    "model": "G1798T"
  },
  {
    "name": "MacBook Pro 16\" ricondizionato con chip Apple M2 Max, CPU 12\u2010core e GPU 38\u2010core - Grigio siderale",
    "family": "mac",
    "store": "it",
    "url": "https://www.apple.com/it/shop/product/G1765T/A/macbook-pro-16-ricondizionato-con-chip-apple-m2-max-cpu-12%E2%80%91core-e-gpu-38%E2%80%91core-grigio-siderale",
    "price": 4469.0,
    "previous_price": 4469.0,
    "savings_price": 0,
    "saving_percentage": 0.0,
    "model": "G1765T"
  },
  {
    "name": "MacBook Pro 14\" ricondizionato con chip Apple M2 Max, CPU 12\u2010core e GPU 38\u2010core - Grigio siderale",
    "family": "mac",
    "store": "it",
    "url": "https://www.apple.com/it/shop/product/G17JHT/A/macbook-pro-14-ricondizionato-con-chip-apple-m2-max-cpu-12-core-e-gpu-38-core-grigio-siderale",
    "price": 4659.0,
    "previous_price": 4659.0,
    "savings_price": 0,
    "saving_percentage": 0.0,
    "model": "G17JHT"
  },
  {
    "name": "MacBook Pro 14\" ricondizionato con chip Apple M1 Max, CPU 10\u2010core e GPU 32\u2010core - Argento",
    "family": "mac",
    "store": "it",
    "url": "https://www.apple.com/it/shop/product/G15KNT/A/macbook-pro-14-ricondizionato-con-chip-apple-m1-max-cpu-10%E2%80%91core-e-gpu-32%E2%80%91core-argento",
    "price": 4839.0,
    "previous_price": 4839.0,
    "savings_price": 0,
    "saving_percentage": 0.0,
    "model": "G15KNT"
  },
  {
    "name": "MacBook Pro 14\" ricondizionato con chip Apple M2 Max, CPU 12\u2010core e GPU 30\u2010core - Grigio siderale",
    "family": "mac",
    "store": "it",
    "url": "https://www.apple.com/it/shop/product/G17J6T/A/macbook-pro-14-ricondizionato-con-chip-apple-m2-max-cpu-12-core-e-gpu-30-core-grigio-siderale",
    "price": 5189.0,
    "previous_price": 5189.0,
    "savings_price": 0,
    "saving_percentage": 0.0,
    "model": "G17J6T"
  },
  {
    "name": "MacBook Pro 16\" ricondizionato con chip Apple M2 Max, CPU 12\u2010core e GPU 38\u2010core - Grigio siderale",
    "family": "mac",
    "store": "it",
    "url": "https://www.apple.com/it/shop/product/G176AT/A/macbook-pro-16-ricondizionato-con-chip-apple-m2-max-cpu-12%E2%80%91core-e-gpu-38%E2%80%91core-grigio-siderale",
    "price": 5869.0,
    "previous_price": 5869.0,
    "savings_price": 0,
    "saving_percentage": 0.0,
    "model": "G176AT"
  }
]